{
    "spawn": {
        "x": 0,
        "y": 0
    },
    "tileset": "..\\testtileset.json",
    "tileSize": 16,
    "dimensions": {
        "width": 16,
        "height": 16
    },
    "tilemap": [
        "0,0,0,0,2,2,2,2,2,2,18,67,67,0,0,0",
        "0,0,0,0,0,18,18,18,18,18,32,83,83,0,0,0",
        "0,0,0,0,0,0,0,0,34,34,102,50,50,0,0,0",
        "0,0,0,0,0,0,0,0,21,22,118,50,50,0,0,0",
        "0,0,0,0,0,0,0,0,37,38,86,50,50,0,0,0",
        "0,0,0,0,0,0,0,0,50,50,50,50,50,0,0,0",
        "0,0,0,0,0,0,0,0,0,0,0,0,0,0,0,0",
        "0,0,0,0,0,0,0,0,0,0,0,0,0,0,0,0",
        "0,0,0,0,0,0,0,0,0,0,0,0,0,0,0,0",
        "0,0,0,0,0,0,0,0,0,0,0,0,0,0,0,0",
        "0,0,0,0,0,0,0,0,0,0,0,0,0,0,0,0",
        "0,0,0,0,0,0,0,0,0,0,0,0,0,0,0,0",
        "0,0,0,0,0,0,0,0,0,0,0,0,0,0,0,0",
        "0,0,0,0,0,0,0,0,0,0,0,0,0,0,0,0",
        "0,0,0,0,0,0,0,0,0,0,0,0,0,0,0,0",
        "0,0,0,0,0,0,0,0,0,0,0,0,0,0,0,0"
    ]
}